pdip/__init__.py
pdip/api/__init__.py
pdip/api/app/__init__.py
pdip/api/app/flask_app_wrapper.py
pdip/api/base/__init__.py
pdip/api/base/controller_base.py
pdip/api/base/endpoint_base.py
pdip/api/base/endpoint_wrapper.py
pdip/api/base/resource_base.py
pdip/api/converter/__init__.py
pdip/api/converter/request_converter.py
pdip/api/decorators/__init__.py
pdip/api/decorators/controller_base.py
pdip/api/handlers/__init__.py
pdip/api/handlers/error_handlers.py
pdip/api/handlers/request_handler.py
pdip/api/request_parameter/__init__.py
pdip/api/request_parameter/order_by_parameter.py
pdip/api/request_parameter/paging_parameter.py
pdip/api/specifications/__init__.py
pdip/api/specifications/order_by_specification.py
pdip/api/specifications/paging_specification.py
pdip/base/__init__.py
pdip/base/pdi.py
pdip/configuration/__init__.py
pdip/configuration/config_manager.py
pdip/configuration/models/__init__.py
pdip/configuration/models/api/__init__.py
pdip/configuration/models/api/api_config.py
pdip/configuration/models/application/__init__.py
pdip/configuration/models/application/application_config.py
pdip/configuration/models/aps/__init__.py
pdip/configuration/models/aps/aps_config.py
pdip/configuration/models/base/__init__.py
pdip/configuration/models/base/base_config.py
pdip/configuration/models/database/__init__.py
pdip/configuration/models/database/database_config.py
pdip/configuration/services/__init__.py
pdip/configuration/services/config_parameter_base.py
pdip/configuration/services/config_service.py
pdip/cqrs/__init__.py
pdip/cqrs/command_query_base.py
pdip/cqrs/command_query_handler_base.py
pdip/cqrs/dispatcher.py
pdip/cqrs/icommand.py
pdip/cqrs/icommand_handler.py
pdip/cqrs/iquery.py
pdip/cqrs/iquery_handler.py
pdip/cqrs/decorators/__init__.py
pdip/cqrs/decorators/cls_to_dict.py
pdip/cqrs/decorators/dto_class.py
pdip/cqrs/decorators/request_class.py
pdip/cqrs/decorators/response_class.py
pdip/cqrs/generator/__init__.py
pdip/cqrs/generator/query_generator.py
pdip-0.6.11.dist-info/LICENSE
pdip-0.6.11.dist-info/METADATA
pdip-0.6.11.dist-info/WHEEL
pdip-0.6.11.dist-info/top_level.txt
pdip-0.6.11.dist-info/RECORD
