Metadata-Version: 2.1
Name: pdip
Version: 0.6.11
Summary: Python Data Integrator infrastructures package
Home-page: https://github.com/ahmetcagriakca/pdip
Author: Ahmet Çağrı AKCA
Author-email: ahmetcagriakca@gmail.com
License: MIT
Download-URL: https://github.com/ahmetcagriakca/pdip/archive/refs/tags/v0.6.11.tar.gz
Project-URL: Bug Reports, https://github.com/ahmetcagriakca/pdip/issues
Project-URL: Source, https://github.com/ahmetcagriakca/pdip
Keywords: PDI,API,ETL,PROCESS,MULTIPROCESS,IO,CQRS,MSSQL,ORACLE,POSTGRES,MYSQL,CSV
Platform: UNKNOWN
Classifier: Intended Audience :: Developers
Classifier: Topic :: Software Development :: Build Tools
Classifier: License :: OSI Approved :: MIT License
Classifier: Operating System :: OS Independent
Classifier: Programming Language :: Python :: 3.8
Classifier: Programming Language :: Python :: 3.9
Classifier: Programming Language :: Python :: 3.10
Classifier: Programming Language :: Python :: 3.11
Requires-Python: >=3.8
Requires-Dist: dataclasses
Requires-Dist: injector
Requires-Dist: PyYAML
Requires-Dist: SQLAlchemy
Provides-Extra: api
Requires-Dist: Flask ==3.0.3 ; extra == 'api'
Requires-Dist: Flask-Cors ==4.0.1 ; extra == 'api'
Requires-Dist: Flask-Ext ==0.1 ; extra == 'api'
Requires-Dist: Flask-Injector ==0.15.0 ; extra == 'api'
Requires-Dist: flask-restx ==1.3.0 ; extra == 'api'
Requires-Dist: markupsafe ==2.1.5 ; extra == 'api'
Requires-Dist: Werkzeug ==3.0.3 ; extra == 'api'
Provides-Extra: cryptography
Requires-Dist: cryptography ==42.0.7 ; extra == 'cryptography'
Requires-Dist: Fernet ==1.0.1 ; extra == 'cryptography'
Provides-Extra: integrator
Requires-Dist: cx-Oracle ==8.3.0 ; extra == 'integrator'
Requires-Dist: dataclasses-json ==0.6.6 ; extra == 'integrator'
Requires-Dist: func-timeout ==4.3.5 ; extra == 'integrator'
Requires-Dist: kafka-python ==2.0.2 ; extra == 'integrator'
Requires-Dist: mysql-connector-python ==8.4.0 ; extra == 'integrator'
Requires-Dist: pandas ==2.2.2 ; extra == 'integrator'
Requires-Dist: psycopg2-binary ==2.9.9 ; extra == 'integrator'
Requires-Dist: pyodbc ==5.1.0 ; extra == 'integrator'
Provides-Extra: preferred
Requires-Dist: dataclasses ==0.6 ; extra == 'preferred'
Requires-Dist: injector ==0.21.0 ; extra == 'preferred'
Requires-Dist: PyYAML ==6.0.1 ; extra == 'preferred'
Requires-Dist: SQLAlchemy ==2.0.30 ; extra == 'preferred'
